cdk_tweet_queue/__init__.py
cdk_tweet_queue/py.typed
cdk_tweet_queue/_jsii/__init__.py
cdk_tweet_queue/_jsii/cdk-tweet-queue@2.0.936.jsii.tgz
cdk_tweet_queue-2.0.936.dist-info/LICENSE
cdk_tweet_queue-2.0.936.dist-info/METADATA
cdk_tweet_queue-2.0.936.dist-info/WHEEL
cdk_tweet_queue-2.0.936.dist-info/top_level.txt
cdk_tweet_queue-2.0.936.dist-info/RECORD
