Metadata-Version: 2.1
Name: cdk-tweet-queue
Version: 2.0.936
Summary: Defines an SQS queue with tweet stream from a search
Home-page: https://github.com/cdklabs/cdk-tweet-queue
Author: Elad Ben-Israel<elad.benisrael@gmail.com>
License: Apache-2.0
Project-URL: Source, https://github.com/cdklabs/cdk-tweet-queue
Classifier: Intended Audience :: Developers
Classifier: Operating System :: OS Independent
Classifier: Programming Language :: JavaScript
Classifier: Programming Language :: Python :: 3 :: Only
Classifier: Programming Language :: Python :: 3.9
Classifier: Programming Language :: Python :: 3.10
Classifier: Programming Language :: Python :: 3.11
Classifier: Typing :: Typed
Classifier: Development Status :: 5 - Production/Stable
Classifier: License :: OSI Approved
Requires-Python: ~=3.9
License-File: LICENSE
Requires-Dist: aws-cdk-lib <3.0.0,>=2.220.0
Requires-Dist: constructs <11.0.0,>=10.4.2
Requires-Dist: jsii <2.0.0,>=1.117.0
Requires-Dist: publication >=0.0.3
Requires-Dist: typeguard <4.3.0,>=2.13.3
